pyeasyscrap/__init__.py
pyeasyscrap/basic_functions.py
pyeasyscrap/web_scraping_functions.py
py_easy_scrap-0.1.3.dist-info/LICENSE
py_easy_scrap-0.1.3.dist-info/METADATA
py_easy_scrap-0.1.3.dist-info/WHEEL
py_easy_scrap-0.1.3.dist-info/top_level.txt
py_easy_scrap-0.1.3.dist-info/RECORD
