Metadata-Version: 2.1
Name: py-easy-scrap
Version: 0.1.3
Summary: A useful package for web scraping with Selenium
Home-page: https://github.com/ygalvao/py-easy-scrap
Author: Yuri Henrique Galvao
Author-email: Yuri Henrique Galvao <yuri@galvao.ca>
License: UNKNOWN
Project-URL: Homepage, https://github.com/ygalvao/py-easy-scrap
Project-URL: Bug Tracker, https://github.com/ygalvao/py-easy-scrap/issues
Platform: UNKNOWN
Classifier: Programming Language :: Python :: 3
Classifier: License :: OSI Approved :: MIT License
Classifier: Operating System :: OS Independent
Requires-Python: >=3.7
License-File: LICENSE
Requires-Dist: selenium
